iso8583/__init__.py
iso8583/decoder.py
iso8583/encoder.py
iso8583/py.typed
iso8583/specs.py
iso8583/tools.py
pyiso8583-4.0.1.dist-info/LICENSE.md
pyiso8583-4.0.1.dist-info/METADATA
pyiso8583-4.0.1.dist-info/WHEEL
pyiso8583-4.0.1.dist-info/top_level.txt
pyiso8583-4.0.1.dist-info/RECORD
